data/countries_names.csv
data/languages_names.csv
majormode/__init__.py
majormode/xebus/__init__.py
majormode/xebus/constant/__init__.py
majormode/xebus/constant/family.py
majormode/xebus/constant/family_sheet.py
majormode/xebus/model/__init__.py
majormode/xebus/model/child.py
majormode/xebus/model/error.py
majormode/xebus/model/family.py
majormode/xebus/model/family_sheet.py
majormode/xebus/model/grade.py
majormode/xebus/model/guardian.py
majormode/xebus/model/person.py
majormode/xebus/model/school_class.py
majormode/xebus/model/sectioned_sheet.py
majormode/xebus/utils/__init__.py
majormode/xebus/utils/csv_utils.py
majormode/xebus/utils/normalization_utils.py
xebus_family_data_library-1.0.14.dist-info/LICENSE.md
xebus_family_data_library-1.0.14.dist-info/METADATA
xebus_family_data_library-1.0.14.dist-info/WHEEL
xebus_family_data_library-1.0.14.dist-info/RECORD
