Metadata-Version: 2.1
Name: xebus-family-data-library
Version: 1.0.14
Summary: Python library for loading family data from sheets
Home-page: https://github.com/xebus/xebus-family-data-python-library
License: SEE LICENSE IN <LICENSE.md>
Keywords: data,family,sheet,xebus
Author: Daniel CAUNE
Author-email: daniel.caune@gmail.com
Requires-Python: >=3.10,<4.0
Classifier: Development Status :: 5 - Production/Stable
Classifier: License :: Other/Proprietary License
Classifier: Operating System :: OS Independent
Classifier: Programming Language :: Python
Classifier: Programming Language :: Python :: 3
Classifier: Programming Language :: Python :: 3.10
Classifier: Programming Language :: Python :: 3.11
Classifier: Topic :: Software Development :: Libraries
Requires-Dist: perseus-core-library (>=1.20.1,<2.0.0)
Requires-Dist: unidecode (>=1.3.8,<2.0.0)
Requires-Dist: xebus-core-library (>=1.4.10,<2.0.0)
Project-URL: Repository, https://github.com/xebus/xebus-family-data-python-library
